odoo8_addon_quality_control-8.0.1.3.0-py2.7-nspkg.pth
odoo8_addon_quality_control-8.0.1.3.0.dist-info/top_level.txt
odoo8_addon_quality_control-8.0.1.3.0.dist-info/WHEEL
odoo8_addon_quality_control-8.0.1.3.0.dist-info/RECORD
odoo8_addon_quality_control-8.0.1.3.0.dist-info/metadata.json
odoo8_addon_quality_control-8.0.1.3.0.dist-info/DESCRIPTION.rst
odoo8_addon_quality_control-8.0.1.3.0.dist-info/METADATA
odoo8_addon_quality_control-8.0.1.3.0.dist-info/namespace_packages.txt
odoo_addons/quality_control/__openerp__.py
odoo_addons/quality_control/__init__.py
odoo_addons/quality_control/README.rst
odoo_addons/quality_control/security/quality_control_security.xml
odoo_addons/quality_control/security/ir.model.access.csv
odoo_addons/quality_control/models/product_template.py
odoo_addons/quality_control/models/qc_test.py
odoo_addons/quality_control/models/product_product.py
odoo_addons/quality_control/models/qc_test_category.py
odoo_addons/quality_control/models/qc_trigger_line.py
odoo_addons/quality_control/models/__init__.py
odoo_addons/quality_control/models/qc_inspection.py
odoo_addons/quality_control/models/qc_trigger.py
odoo_addons/quality_control/models/product_category.py
odoo_addons/quality_control/i18n/ja.po
odoo_addons/quality_control/i18n/nl_NL.po
odoo_addons/quality_control/i18n/lv.po
odoo_addons/quality_control/i18n/zh_CN.po
odoo_addons/quality_control/i18n/nb_NO.po
odoo_addons/quality_control/i18n/uk.po
odoo_addons/quality_control/i18n/es_AR.po
odoo_addons/quality_control/i18n/ko.po
odoo_addons/quality_control/i18n/tr_TR.po
odoo_addons/quality_control/i18n/ru.po
odoo_addons/quality_control/i18n/gl_ES.po
odoo_addons/quality_control/i18n/pt.po
odoo_addons/quality_control/i18n/fr_CH.po
odoo_addons/quality_control/i18n/it.po
odoo_addons/quality_control/i18n/es_CL.po
odoo_addons/quality_control/i18n/es.po
odoo_addons/quality_control/i18n/nl_BE.po
odoo_addons/quality_control/i18n/fr_FR.po
odoo_addons/quality_control/i18n/ar.po
odoo_addons/quality_control/i18n/lt.po
odoo_addons/quality_control/i18n/vi_VN.po
odoo_addons/quality_control/i18n/ro.po
odoo_addons/quality_control/i18n/tr.po
odoo_addons/quality_control/i18n/sr.po
odoo_addons/quality_control/i18n/es_PY.po
odoo_addons/quality_control/i18n/mk.po
odoo_addons/quality_control/i18n/hr.po
odoo_addons/quality_control/i18n/bg.po
odoo_addons/quality_control/i18n/es_EC.po
